{
    "$schema": "https://schema.management.azure.com/schemas/2019-04-01/deploymentParameters.json#",
    "contentVersion": "1.0.0.0",
    "parameters": {
        "resourceGroupName": {
            "value": "azure-bicep-workshop"
        },
        "tags": {
            "value": {
                "purpose": "Azure Bicep Workshop",
                "environment": "dev"
            }
        },
        "tenantId": {
            "value": "b6c6d0d2-60b7-43c5-a090-b456fdea25b7"
        },
        "objectId": {
            "value": "96207a7c-69eb-492a-acc7-6effad0eddbb"
        },
        "subscriptionId": {
            "value": "aaa23b5d-5921-4c88-84cb-ce7b7a6dcce1"
        },
        "location": {
            "value": "westeurope"
        },
        "groups": {
            "value": {
                "owner": "123c92cb-d6ca-4320-a918-10b9f23ebfaf",
                "contributor": "bc0b5b41-4740-42a5-aee6-111af73ca5ce",
                "reader": "e455d04a-c65e-4a55-9b62-0f9c04183420"
            }
        }
    }
}